<?xml version = '1.0' encoding = 'UTF-8'?>
<Relation class="oracle.dbtools.crest.model.design.logical.Relation" name="Relation_3" directorySegmentName="seg_0" id="D6746AC3-F764-3AEF-C103-5F58E29E964E">
<createdBy>skshm</createdBy>
<createdTime>2021-04-05 19:30:55 UTC</createdTime>
<ownerDesignName>PROJECT1</ownerDesignName>
<engineerTo>
<item key="5A0D3FB3-738E-46D8-A660-231C8BF4EFFF" value="true"/>
</engineerTo>
<sourcePk>E84CFCC6-608C-2AC4-F0BD-B2318E121C0C</sourcePk>
<identifying>false</identifying>
<optionalSource>false</optionalSource>
<optionalTarget>false</optionalTarget>
<sourceCardinality>1</sourceCardinality>
<sourceEntity>EF0C82E0-DCF6-7145-41A8-E7FFC5327B3A</sourceEntity>
<targetCardinalityString>*</targetCardinalityString>
<targetEntity>AF4818E0-B015-6B76-8852-7A5AA502AD22</targetEntity>
<transferable>true</transferable>
<deleteRule>NO ACTION</deleteRule>
</Relation>